[{"version": "2022.01", "created_at": "2025-05-25T00:40:40.914070+07:00", "id": "2ba37d79-e572-4b38-a348-bdd4902142c5", "type": "donation", "amount_raw": 5000, "cut": -286, "donator_name": "GKSS", "donator_email": "GKSS@gmail.com", "donator_is_user": false, "message": "hello", "etc": {"amount_to_display": 5000}}, {"version": "2022.01", "created_at": "2025-05-28T21:37:14.998730+07:00", "id": "1692d73f-4505-4832-b0fc-29ef15831029", "type": "donation", "amount_raw": 2500, "cut": -143, "donator_name": "PANDBEAR", "donator_email": "alifcahyagithub@gmail.com", "donator_is_user": false, "message": "PANDBEAR", "etc": {"amount_to_display": 2500}}, {"created_at": "2025-06-01 19:50:19", "donator_name": "LOPIRUZEJ2", "amount_raw": 1.0}, {"created_at": "2025-06-01 19:52:07", "donator_name": "LOPIRUZEJ2", "amount_raw": 1.0}, {"created_at": "2025-06-01 20:10:50", "donator_name": "Julianto8w", "amount_raw": 100.0}, {"created_at": "2025-06-01 20:23:31", "donator_name": "Julianto8w", "amount_raw": 4.0}, {"created_at": "2025-06-01 20:23:54", "donator_name": "Julianto8w", "amount_raw": 100.0}, {"created_at": "2025-06-01 20:29:14", "donator_name": "Julianto8w", "amount_raw": 1.0}, {"created_at": "2025-06-01 20:29:37", "donator_name": "Julianto8w", "amount_raw": 3.0}, {"created_at": "2025-06-01 20:29:49", "donator_name": "Julianto8w", "amount_raw": 100.0}, {"created_at": "2025-06-01 20:39:28", "donator_name": "Julianto8w", "amount_raw": 2.0}, {"created_at": "2025-06-01 20:41:42", "donator_name": "Julianto8w", "amount_raw": 1.0}, {"created_at": "2025-06-01 20:42:49", "donator_name": "Julianto8w", "amount_raw": 1.0}, {"created_at": "2025-06-01 20:44:30", "donator_name": "Julianto8w", "amount_raw": 2.0}]